alloniadb/__init__.py
alloniadb/configs.py
alloniadb/connectors.py
alloniadb-1.0.1.dist-info/METADATA
alloniadb-1.0.1.dist-info/WHEEL
alloniadb-1.0.1.dist-info/RECORD
